asdk_plugin_portfolio/__init__.py
asdk_plugin_portfolio/api_registry.py
asdk_plugin_portfolio/domain_apis_list.json
asdk_plugin_portfolio/agraph/__init__.py
asdk_plugin_portfolio/agraph/portfolio/__init__.py
asdk_plugin_portfolio/agraph/portfolio/configuration/__init__.py
asdk_plugin_portfolio/agraph/portfolio/configuration/portfolio_group/__init__.py
asdk_plugin_portfolio/agraph/portfolio/configuration/portfolio_group/v1/__init__.py
asdk_plugin_portfolio/agraph/portfolio/configuration/portfolio_group/v1/PortfolioGroupAPI/__init__.py
asdk_plugin_portfolio/agraph/portfolio/configuration/portfolio_group/v1/PortfolioGroupAPI/api_client.py
asdk_plugin_portfolio/agraph/portfolio/configuration/portfolio_group/v1/PortfolioGroupAPI/api_response.py
asdk_plugin_portfolio/agraph/portfolio/configuration/portfolio_group/v1/PortfolioGroupAPI/configuration.py
asdk_plugin_portfolio/agraph/portfolio/configuration/portfolio_group/v1/PortfolioGroupAPI/exceptions.py
asdk_plugin_portfolio/agraph/portfolio/configuration/portfolio_group/v1/PortfolioGroupAPI/rest.py
asdk_plugin_portfolio/agraph/portfolio/configuration/portfolio_group/v1/PortfolioGroupAPI/swagger.json
asdk_plugin_portfolio/agraph/portfolio/configuration/portfolio_group/v1/PortfolioGroupAPI/api/__init__.py
asdk_plugin_portfolio/agraph/portfolio/configuration/portfolio_group/v1/PortfolioGroupAPI/api/default_portfolio_group_api.py
asdk_plugin_portfolio/agraph/portfolio/configuration/portfolio_group/v1/PortfolioGroupAPI/models/__init__.py
asdk_plugin_portfolio/agraph/portfolio/configuration/portfolio_group/v1/PortfolioGroupAPI/models/any.py
asdk_plugin_portfolio/agraph/portfolio/configuration/portfolio_group/v1/PortfolioGroupAPI/models/portfolio_group_apiis_child400_response.py
asdk_plugin_portfolio/agraph/portfolio/configuration/portfolio_group/v1/PortfolioGroupAPI/models/rpc_status.py
asdk_plugin_portfolio/agraph/portfolio/configuration/portfolio_group/v1/PortfolioGroupAPI/models/v1_is_ancestor_response.py
asdk_plugin_portfolio-2.0.0b2.dist-info/METADATA
asdk_plugin_portfolio-2.0.0b2.dist-info/WHEEL
asdk_plugin_portfolio-2.0.0b2.dist-info/top_level.txt
asdk_plugin_portfolio-2.0.0b2.dist-info/RECORD
